coldpaper_first/__init__.py
coldpaper_first/main.py
coldpaper_first-0.1.0.dist-info/METADATA
coldpaper_first-0.1.0.dist-info/WHEEL
coldpaper_first-0.1.0.dist-info/entry_points.txt
coldpaper_first-0.1.0.dist-info/RECORD
