Metadata-Version: 2.1
Name: coldpaper_first
Version: 0.1.0
Summary: coldpaper_first
Author: coldpaper1
Author-email: mhkim4869@gmail.com
Requires-Python: >=3.11,<4.0
Classifier: Programming Language :: Python :: 3
Classifier: Programming Language :: Python :: 3.11
Classifier: Programming Language :: Python :: 3.12
Classifier: Programming Language :: Python :: 3.13
Requires-Dist: fastapi (>=0.115.5,<0.116.0)
Requires-Dist: httpx (>=0.27.0,<0.28.0)
Requires-Dist: pytest (>=8.3.4,<9.0.0)
